python_paginate/__init__.py
python_paginate/css/__init__.py
python_paginate/css/basecss.py
python_paginate/css/bootstrap.py
python_paginate/css/foundation.py
python_paginate/css/ink.py
python_paginate/css/metro.py
python_paginate/css/semantic.py
python_paginate/css/uikit.py
python_paginate/web/__init__.py
python_paginate/web/base_paginate.py
python_paginate/web/flask_paginate.py
python_paginate/web/sanic_paginate.py
python_paginate/web/tornado_paginate.py
python_paginate-2024.5.15.dist-info/LICENSE
python_paginate-2024.5.15.dist-info/METADATA
python_paginate-2024.5.15.dist-info/WHEEL
python_paginate-2024.5.15.dist-info/top_level.txt
python_paginate-2024.5.15.dist-info/RECORD
